LICENSE
README.md
setup.cfg
setup.py
servalfix/__init__.py
servalfix/acm.py
servalfix/client.py
servalfix/socket.py
servalfix/sub_client.py
servalfix.egg-info/PKG-INFO
servalfix.egg-info/SOURCES.txt
servalfix.egg-info/dependency_links.txt
servalfix.egg-info/requires.txt
servalfix.egg-info/top_level.txt
servalfix/asyncfix/__init__.py
servalfix/asyncfix/acm.py
servalfix/asyncfix/client.py
servalfix/asyncfix/socket.py
servalfix/asyncfix/sub_client.py
servalfix/lib/__init__.py
servalfix/lib/util/__init__.py
servalfix/lib/util/device.py
servalfix/lib/util/exceptions.py
servalfix/lib/util/headers.py
servalfix/lib/util/helpers.py
servalfix/lib/util/objects.py