Metadata-Version: 2.1
Name: servalfix
Version: 2.3.4.11
Summary: Library for AminoApps. Discord - https://discord.gg/7NmhxQBmET
Home-page: https://github.com/TheSabaru/servalfix
Author: Capuchino
Author-email: chocolabienid@gmail.com
License: MIT
Keywords: aminoapps,servalfix,servalfix,serval,serval-bot,narvii,amino,api,python,python3,python3.x,servalfix.py,serval-amino,capuchino
Requires-Python: >=3.6
License-File: LICENSE
